chatgpt/VERSION
chatgpt/__init__.py
chatgpt/main.py
chatgpt/core/__init__.py
chatgpt/core/gpt.py
asst-2.1.1.dist-info/LICENSE
asst-2.1.1.dist-info/METADATA
asst-2.1.1.dist-info/WHEEL
asst-2.1.1.dist-info/entry_points.txt
asst-2.1.1.dist-info/top_level.txt
asst-2.1.1.dist-info/RECORD
